LICENSE
MANIFEST.in
README.md
setup.cfg
setup.py
pysnappy/__init__.py
pysnappy/cli.py
pysnappy/core.c
pysnappy/core.pxd
pysnappy/core.pyx
pysnappy/crc32c.c
pysnappy/crc32c.pxd
pysnappy/crc32c.pyx
pysnappy/framing.c
pysnappy/framing.pxd
pysnappy/framing.pyx
pysnappy/snappy.pxd
pysnappy.egg-info/PKG-INFO
pysnappy.egg-info/SOURCES.txt
pysnappy.egg-info/dependency_links.txt
pysnappy.egg-info/entry_points.txt
pysnappy.egg-info/top_level.txt
tests/__init__.py