Metadata-Version: 1.1
Name: pysnappy
Version: 0.6.1
Summary: Cython bindings to libsnappy
Home-page: https://github.com/aeroevan/pysnappy
Author: Evan McClain
Author-email: aeroevan@gmail.com
License: MIT
Download-URL: https://github.com/aeroevan/pysnappy/tarball/v0.6.1
Platform: UNKNOWN
Classifier: Development Status :: 3 - Alpha
Classifier: License :: OSI Approved :: MIT License
Classifier: Intended Audience :: Developers
Classifier: Operating System :: OS Independent
Classifier: Programming Language :: Python
Classifier: Programming Language :: Python :: 2
Classifier: Programming Language :: Python :: 2.7
Classifier: Programming Language :: Python :: 3
Classifier: Programming Language :: Python :: 3.7
Classifier: Programming Language :: Cython
